languageflow/VERSION
languageflow/__init__.py
languageflow/cli.py
languageflow/data.py
languageflow/data_fetcher.py
languageflow/datasets.py
languageflow/experiment.py
languageflow/file_utils.py
languageflow/flow.py
languageflow/model_profiling.py
languageflow/api/__init__.py
languageflow/board/__init__.py
languageflow/board/board/count.json
languageflow/board/board/index.html
languageflow/board/board/multilabel.json
languageflow/board/board/result.json
languageflow/board/board/tfidf.json
languageflow/board/board/web/app.js
languageflow/board/board/web/controller.js
languageflow/board/board/web/route.js
languageflow/board/board/web/style.css
languageflow/board/board/web/common/navbar.html
languageflow/board/board/web/count/component.html
languageflow/board/board/web/count/controller.js
languageflow/board/board/web/count/style.css
languageflow/board/board/web/multiclass/component.html
languageflow/board/board/web/multiclass/controller.js
languageflow/board/board/web/multilabel/component.html
languageflow/board/board/web/multilabel/controller.js
languageflow/board/board/web/result/component.html
languageflow/board/board/web/result/controller.js
languageflow/board/board/web/tfidf/component.html
languageflow/board/board/web/tfidf/controller.js
languageflow/board/board/web/tfidf/style.css
languageflow/board/multiclass/index.html
languageflow/board/multiclass/result.json
languageflow/corpus/__init__.py
languageflow/corpus/util.py
languageflow/corpus/vlsp2016_sa_corpus.py
languageflow/data/aivivn2019_sa_sample/dev.txt
languageflow/data/aivivn2019_sa_sample/test.txt
languageflow/data/aivivn2019_sa_sample/train.txt
languageflow/data/uts2017_bank_sample/test.txt
languageflow/data/uts2017_bank_sample/train.txt
languageflow/data/vlsp2016_sa_raw_sample/SA2016-TestData-Ans/test_raw_ANS.txt
languageflow/data/vlsp2016_sa_raw_sample/SA2016-TestData-Ans/test_tokenized_ANS.txt
languageflow/data/vlsp2016_sa_raw_sample/SA2016-training-data-ws/train_negative_tokenized.txt
languageflow-1.1.13.dist-info/AUTHORS.rst
languageflow-1.1.13.dist-info/LICENSE
languageflow-1.1.13.dist-info/METADATA
languageflow-1.1.13.dist-info/WHEEL
languageflow-1.1.13.dist-info/entry_points.txt
languageflow-1.1.13.dist-info/top_level.txt
languageflow-1.1.13.dist-info/RECORD
