Metadata-Version: 2.1
Name: languageflow
Version: 1.1.13
Summary: Data loaders and abstractions for text and NLP
Home-page: https://github.com/undertheseanlp/languageflow
Author: Vu Anh
Author-email: anhv.ict91@gmail.com
License: GNU General Public License v3
Keywords: languageflow
Platform: UNKNOWN
Classifier: Development Status :: 2 - Pre-Alpha
Classifier: Intended Audience :: Developers
Classifier: License :: OSI Approved :: GNU General Public License v3 (GPLv3)
Classifier: Natural Language :: English
Classifier: Programming Language :: Python :: 3.6
Requires-Dist: Click (>=6.0)
Requires-Dist: requests
Requires-Dist: tabulate
Requires-Dist: clint
Requires-Dist: tqdm
Requires-Dist: scikit-learn (==0.20.3)
Requires-Dist: joblib (==0.13.2)
